.gitignore
LICENSE.txt
MANIFEST.in
README.md
pyproject.toml
setup.cfg
setup.py
.github/workflows/pytest.yml
ElMD/ElMD.py
ElMD/__init__.py
ElMD/test_ElMD.py
ElMD.egg-info/PKG-INFO
ElMD.egg-info/SOURCES.txt
ElMD.egg-info/dependency_links.txt
ElMD.egg-info/requires.txt
ElMD.egg-info/top_level.txt
ElMD/el_lookup/__init__.py
ElMD/el_lookup/atomic.json
ElMD/el_lookup/cgcnn.json
ElMD/el_lookup/elemnet.json
ElMD/el_lookup/jarvis.json
ElMD/el_lookup/jarvis_sc.json
ElMD/el_lookup/magpie.json
ElMD/el_lookup/magpie_sc.json
ElMD/el_lookup/mat2vec.json
ElMD/el_lookup/matscholar.json
ElMD/el_lookup/megnet16.json
ElMD/el_lookup/mendeleev.json
ElMD/el_lookup/mod_petti.json
ElMD/el_lookup/oliynyk.json
ElMD/el_lookup/oliynyk_sc.json
ElMD/el_lookup/petti.json
ElMD/el_lookup/random_200.json