Metadata-Version: 2.1
Name: ElMD
Version: 0.5.15
Summary: An implementation of the Element movers distance for chemical similarity of ionic compositions
Home-page: https://github.com/lrcfmd/ElMD/
Author: Cameron Hagreaves
Author-email: cameron.h@rgreaves.me.uk
License: GPL3
Download-URL: https://github.com/lrcfmd/ElMD/archive/v0.5.12.tar.gz
Keywords: ChemInformatics,Materials Science,Machine Learning,Materials Representation
Platform: UNKNOWN
Classifier: Development Status :: 5 - Production/Stable
Classifier: Intended Audience :: Developers
Classifier: Topic :: Software Development :: Build Tools
Classifier: License :: OSI Approved :: GNU Lesser General Public License v3 (LGPLv3) 
Classifier: Programming Language :: Python :: 3
Classifier: Programming Language :: Python :: 3.4
Classifier: Programming Language :: Python :: 3.5
Classifier: Programming Language :: Python :: 3.6
Classifier: Programming Language :: Python :: 3.7
License-File: LICENSE.txt
